{
"meta":{"test_sets":[],"test_metrics":[],"learn_metrics":[{"best_value":"Min","name":"Logloss"}],"launch_mode":"Train","parameters":"","iteration_count":105,"learn_sets":["learn"],"name":"experiment"},
"iterations":[
{"learn":[0.6277231383],"iteration":0,"passed_time":0.05091529576,"remaining_time":5.295190759},
{"learn":[0.5764161513],"iteration":1,"passed_time":0.05197791681,"remaining_time":2.676862716},
{"learn":[0.5358362882],"iteration":2,"passed_time":0.05315793963,"remaining_time":1.807369947},
{"learn":[0.5032601391],"iteration":3,"passed_time":0.05440536385,"remaining_time":1.373735437},
{"learn":[0.4747393843],"iteration":4,"passed_time":0.06285312901,"remaining_time":1.25706258},
{"learn":[0.4517497242],"iteration":5,"passed_time":0.06554728179,"remaining_time":1.08153015},
{"learn":[0.4337900192],"iteration":6,"passed_time":0.06744861915,"remaining_time":0.9442806681},
{"learn":[0.4192106237],"iteration":7,"passed_time":0.06990466706,"remaining_time":0.8475940881},
{"learn":[0.4049569639],"iteration":8,"passed_time":0.0727816232,"remaining_time":0.7763373142},
{"learn":[0.393213006],"iteration":9,"passed_time":0.07523987153,"remaining_time":0.7147787796},
{"learn":[0.3843735954],"iteration":10,"passed_time":0.07785982277,"remaining_time":0.6653475764},
{"learn":[0.379014919],"iteration":11,"passed_time":0.07928735055,"remaining_time":0.6144769667},
{"learn":[0.3740007062],"iteration":12,"passed_time":0.08021956879,"remaining_time":0.5677077176},
{"learn":[0.3700081792],"iteration":13,"passed_time":0.08113098678,"remaining_time":0.5273514141},
{"learn":[0.3655199069],"iteration":14,"passed_time":0.08357343468,"remaining_time":0.5014406081},
{"learn":[0.3603218422],"iteration":15,"passed_time":0.08626868753,"remaining_time":0.4798695744},
{"learn":[0.3557958089],"iteration":16,"passed_time":0.08903324143,"remaining_time":0.4608779556},
{"learn":[0.3515958166],"iteration":17,"passed_time":0.09143428859,"remaining_time":0.4419323948},
{"learn":[0.3475940613],"iteration":18,"passed_time":0.09535946533,"remaining_time":0.4316270536},
{"learn":[0.3453532331],"iteration":19,"passed_time":0.09801741751,"remaining_time":0.4165740244},
{"learn":[0.3425002891],"iteration":20,"passed_time":0.1004482652,"remaining_time":0.4017930608},
{"learn":[0.340300445],"iteration":21,"passed_time":0.1027832108,"remaining_time":0.3877730225},
{"learn":[0.337798716],"iteration":22,"passed_time":0.1052672592,"remaining_time":0.3753006631},
{"learn":[0.3372162527],"iteration":23,"passed_time":0.1062475784,"remaining_time":0.3585855771},
{"learn":[0.3344623424],"iteration":24,"passed_time":0.1086523253,"remaining_time":0.3476874409},
{"learn":[0.3320021743],"iteration":25,"passed_time":0.1118738881,"remaining_time":0.3399245062},
{"learn":[0.3307138542],"iteration":26,"passed_time":0.1143875373,"remaining_time":0.3304528855},
{"learn":[0.3291903162],"iteration":27,"passed_time":0.116726783,"remaining_time":0.3209986532},
{"learn":[0.3279011479],"iteration":28,"passed_time":0.1200005466,"remaining_time":0.3144841911},
{"learn":[0.326518001],"iteration":29,"passed_time":0.1222772911,"remaining_time":0.3056932278},
{"learn":[0.3255857475],"iteration":30,"passed_time":0.1253319506,"remaining_time":0.2991794951},
{"learn":[0.3252062371],"iteration":31,"passed_time":0.1267030774,"remaining_time":0.2890413953},
{"learn":[0.3238550497],"iteration":32,"passed_time":0.1300702434,"remaining_time":0.2837896219},
{"learn":[0.322500741],"iteration":33,"passed_time":0.1331373033,"remaining_time":0.2780220157},
{"learn":[0.3215594628],"iteration":34,"passed_time":0.1445269259,"remaining_time":0.2890538519},
{"learn":[0.3205080568],"iteration":35,"passed_time":0.1517256669,"remaining_time":0.2908075281},
{"learn":[0.320119386],"iteration":36,"passed_time":0.1541198137,"remaining_time":0.2832472252},
{"learn":[0.3194738179],"iteration":37,"passed_time":0.1568001661,"remaining_time":0.2764634508},
{"learn":[0.3187014636],"iteration":38,"passed_time":0.1605365392,"remaining_time":0.2716772203},
{"learn":[0.3179783718],"iteration":39,"passed_time":0.1643823143,"remaining_time":0.2671212608},
{"learn":[0.316937551],"iteration":40,"passed_time":0.1668950637,"remaining_time":0.2605191239},
{"learn":[0.3158215814],"iteration":41,"passed_time":0.1708862419,"remaining_time":0.2563293628},
{"learn":[0.3147316],"iteration":42,"passed_time":0.173643496,"remaining_time":0.2503696918},
{"learn":[0.3135467919],"iteration":43,"passed_time":0.1760809435,"remaining_time":0.2441122171},
{"learn":[0.312821393],"iteration":44,"passed_time":0.1793351071,"remaining_time":0.2391134761},
{"learn":[0.3119797932],"iteration":45,"passed_time":0.1820767602,"remaining_time":0.2335332359},
{"learn":[0.3113871856],"iteration":46,"passed_time":0.1847842131,"remaining_time":0.2280315821},
{"learn":[0.3110220943],"iteration":47,"passed_time":0.1876439688,"remaining_time":0.222827213},
{"learn":[0.3104302331],"iteration":48,"passed_time":0.1900622161,"remaining_time":0.2172139613},
{"learn":[0.3093957228],"iteration":49,"passed_time":0.1946186053,"remaining_time":0.2140804658},
{"learn":[0.3089504274],"iteration":50,"passed_time":0.197157655,"remaining_time":0.2087551641},
{"learn":[0.3082412796],"iteration":51,"passed_time":0.1996726042,"remaining_time":0.203512462},
{"learn":[0.3072106031],"iteration":52,"passed_time":0.2024411583,"remaining_time":0.1986215138},
{"learn":[0.3060390945],"iteration":53,"passed_time":0.2048793058,"remaining_time":0.1934971222},
{"learn":[0.3053263505],"iteration":54,"passed_time":0.2102290103,"remaining_time":0.1911172821},
{"learn":[0.3046130636],"iteration":55,"passed_time":0.2129694638,"remaining_time":0.1863482808},
{"learn":[0.3039591494],"iteration":56,"passed_time":0.2156039153,"remaining_time":0.1815611919},
{"learn":[0.3030830116],"iteration":57,"passed_time":0.217990862,"remaining_time":0.1766477675},
{"learn":[0.3025593781],"iteration":58,"passed_time":0.2204761106,"remaining_time":0.1718966286},
{"learn":[0.3015478366],"iteration":59,"passed_time":0.2241652824,"remaining_time":0.1681239618},
{"learn":[0.3008817086],"iteration":60,"passed_time":0.2265068281,"remaining_time":0.1633819744},
{"learn":[0.3002344781],"iteration":61,"passed_time":0.2293289832,"remaining_time":0.1590507464},
{"learn":[0.2997931183],"iteration":62,"passed_time":0.2323627427,"remaining_time":0.1549084951},
{"learn":[0.2991842256],"iteration":63,"passed_time":0.2354126021,"remaining_time":0.1508111982},
{"learn":[0.2987076832],"iteration":64,"passed_time":0.2386019646,"remaining_time":0.1468319782},
{"learn":[0.2981561615],"iteration":65,"passed_time":0.2413129177,"remaining_time":0.1425939968},
{"learn":[0.2977905613],"iteration":66,"passed_time":0.2466396215,"remaining_time":0.1398851585},
{"learn":[0.2971252815],"iteration":67,"passed_time":0.2492841735,"remaining_time":0.1356399179},
{"learn":[0.2966690615],"iteration":68,"passed_time":0.2517821221,"remaining_time":0.1313645854},
{"learn":[0.2961550294],"iteration":69,"passed_time":0.253987665,"remaining_time":0.1269938325},
{"learn":[0.2956163323],"iteration":70,"passed_time":0.2565642151,"remaining_time":0.1228617368},
{"learn":[0.2947917979],"iteration":71,"passed_time":0.2589847624,"remaining_time":0.1187013495},
{"learn":[0.2941808356],"iteration":72,"passed_time":0.2613476089,"remaining_time":0.1145633354},
{"learn":[0.2939463303],"iteration":73,"passed_time":0.2639366596,"remaining_time":0.1105680601},
{"learn":[0.2933441552],"iteration":74,"passed_time":0.2665804113,"remaining_time":0.1066321645},
{"learn":[0.2928822015],"iteration":75,"passed_time":0.2693805663,"remaining_time":0.1027899529},
{"learn":[0.2923059469],"iteration":76,"passed_time":0.2718465142,"remaining_time":0.0988532779},
{"learn":[0.2918539],"iteration":77,"passed_time":0.2742176607,"remaining_time":0.09492149793},
{"learn":[0.2914860266],"iteration":78,"passed_time":0.2768267117,"remaining_time":0.09110752537},
{"learn":[0.2910955237],"iteration":79,"passed_time":0.2790855558,"remaining_time":0.08721423619},
{"learn":[0.2907977441],"iteration":80,"passed_time":0.2815657042,"remaining_time":0.08342687531},
{"learn":[0.2902566041],"iteration":81,"passed_time":0.2842080554,"remaining_time":0.07971689358},
{"learn":[0.289461349],"iteration":82,"passed_time":0.2868553071,"remaining_time":0.07603393682},
{"learn":[0.2886475017],"iteration":83,"passed_time":0.2892606541,"remaining_time":0.07231516352},
{"learn":[0.2880883803],"iteration":84,"passed_time":0.2929674264,"remaining_time":0.06893351209},
{"learn":[0.2874681898],"iteration":85,"passed_time":0.2956573787,"remaining_time":0.06531965343},
{"learn":[0.286609762],"iteration":86,"passed_time":0.2983062307,"remaining_time":0.06171853049},
{"learn":[0.2860123707],"iteration":87,"passed_time":0.3007356781,"remaining_time":0.05809666509},
{"learn":[0.2855127577],"iteration":88,"passed_time":0.3034810318,"remaining_time":0.05455838774},
{"learn":[0.2851768099],"iteration":89,"passed_time":0.3060535823,"remaining_time":0.05100893038},
{"learn":[0.2847006068],"iteration":90,"passed_time":0.3084110283,"remaining_time":0.04744785051},
{"learn":[0.2844016227],"iteration":91,"passed_time":0.3109285775,"remaining_time":0.04393555986},
{"learn":[0.2840380751],"iteration":92,"passed_time":0.313305024,"remaining_time":0.0404264547},
{"learn":[0.2836585647],"iteration":93,"passed_time":0.315746172,"remaining_time":0.03694902013},
{"learn":[0.2831525394],"iteration":94,"passed_time":0.3182208206,"remaining_time":0.03349692849},
{"learn":[0.2825596944],"iteration":95,"passed_time":0.3206372676,"remaining_time":0.03005974383},
{"learn":[0.2821762314],"iteration":96,"passed_time":0.3233793208,"remaining_time":0.02667045944},
{"learn":[0.2817331582],"iteration":97,"passed_time":0.325753167,"remaining_time":0.02326808336},
{"learn":[0.2814036736],"iteration":98,"passed_time":0.3280726124,"remaining_time":0.01988318863},
{"learn":[0.2811311867],"iteration":99,"passed_time":0.3304970597,"remaining_time":0.01652485298},
{"learn":[0.2807197846],"iteration":100,"passed_time":0.3331753122,"remaining_time":0.01319506187},
{"learn":[0.2802546927],"iteration":101,"passed_time":0.3359106657,"remaining_time":0.00987972546},
{"learn":[0.2800145724],"iteration":102,"passed_time":0.3384017145,"remaining_time":0.006570907078},
{"learn":[0.2796758765],"iteration":103,"passed_time":0.3406843591,"remaining_time":0.003275811146},
{"learn":[0.2792962304],"iteration":104,"passed_time":0.3430584057,"remaining_time":0}
]}